README.rst
setup.py
extor/__init__.py
extor/handlers/__init__.py
extor/model/__init__.py
extor/model/ext_model.py
extor/modules/__init__.py
torcms_app/__init__.py
torcms_app.egg-info/PKG-INFO
torcms_app.egg-info/SOURCES.txt
torcms_app.egg-info/dependency_links.txt
torcms_app.egg-info/top_level.txt
torcms_app.egg-info/zip-safe
torcms_app/handlers/__init__.py
torcms_app/handlers/app_calcinfo_handler.py
torcms_app/handlers/app_handler.py
torcms_app/handlers/javascript_handler.py
torcms_app/model/__init__.py
torcms_app/model/ext.py
torcms_app/model/ext_model.py
torcms_app/script/__init__.py
torcms_app/script/command.py
torcms_app/script/script_fix_app_path.py
torcms_app/script/autogen_convert/__init__.py
torcms_app/script/autogen_convert/arr_lisan.py
torcms_app/script/autogen_convert/generate_classed.py
torcms_app/script/autogen_formula/__init__.py
torcms_app/script/autogen_formula/generate_app_html.py
torcms_app/script/autogen_formula/script_formula_dic2yaml.py